vcpkg_sbom/__init__.py
vcpkg_sbom-0.0.6.dist-info/LICENSE
vcpkg_sbom-0.0.6.dist-info/METADATA
vcpkg_sbom-0.0.6.dist-info/WHEEL
vcpkg_sbom-0.0.6.dist-info/entry_points.txt
vcpkg_sbom-0.0.6.dist-info/top_level.txt
vcpkg_sbom-0.0.6.dist-info/RECORD
