Metadata-Version: 2.1
Name: vcpkg-sbom
Version: 0.0.6
Summary: A python CLI tool to extract a merged software bill of materials and license info from a vcpkg manifest.
Home-page: https://github.com/moverseai/vcpkg-sbom/
Author: Moverse P.C.
Author-email: info@moverse.ai
Project-URL: Documentation, https://github.com/moverseai/vcpkg-sbom/
Project-URL: Source, https://github.com/moverseai/vcpkg-sbom/
Keywords: software-bill-of-materials,developer-tools,sbom,spdx,vcpkg,license,eula,cpp,c++,dependencies,oss
Classifier: Development Status :: 3 - Alpha
Classifier: Intended Audience :: Developers
Classifier: Intended Audience :: Science/Research
Classifier: Programming Language :: Python :: 3.8
Classifier: Programming Language :: Python :: 3.9
Classifier: Programming Language :: Python :: 3.10
Classifier: Programming Language :: Python :: 3.11
Classifier: Programming Language :: Python :: 3.12
Classifier: License :: OSI Approved :: MIT License
Classifier: Operating System :: Microsoft :: Windows
Classifier: Operating System :: POSIX :: Linux
Classifier: Topic :: Software Development
Classifier: Topic :: Software Development :: Libraries
Classifier: Topic :: Software Development :: Build Tools
Classifier: Topic :: System :: Software Distribution
Classifier: Environment :: Console
Requires-Python: >=3.8
License-File: LICENSE
Requires-Dist: spdx-tools ==0.8.3
Requires-Dist: toolz ==0.11.2
